[{"ent_seq":1306630,"k_ele":[{"keb":"司る","ke_pri":["spec1"]},{"keb":"掌る","ke_inf":["rarely used kanji form"]},{"keb":"司どる","ke_inf":["search-only kanji form"]}],"r_ele":[{"reb":"つかさどる","re_pri":["spec1"]}],"sense":[{"pos":["Godan verb with 'ru' ending","transitive verb"],"gloss":[{"value":"to be in charge of","lang":"eng"},{"value":"to manage","lang":"eng"},{"value":"to direct","lang":"eng"},{"value":"to administer","lang":"eng"},{"value":"to preside over","lang":"eng"}]},{"pos":["Godan verb with 'ru' ending","transitive verb"],"gloss":[{"value":"to rule","lang":"eng"},{"value":"to govern","lang":"eng"},{"value":"to control","lang":"eng"}]}]},{"ent_seq":1306640,"k_ele":[{"keb":"司会","ke_pri":["ichi1","news1","nf08"]}],"r_ele":[{"reb":"しかい","re_pri":["ichi1","news1","nf08"]}],"sense":[{"pos":["noun (common) (futsuumeishi)","noun or participle which takes the aux. verb suru","transitive verb","intransitive verb"],"gloss":[{"value":"leading a meeting","lang":"eng"},{"value":"presiding over a meeting","lang":"eng"},{"value":"officiating at a ceremony","lang":"eng"},{"value":"chairmanship","lang":"eng"}]},{"pos":["noun (common) (futsuumeishi)"],"xref":["司会者"],"gloss":[{"value":"chairman","lang":"eng"},{"value":"presenter","lang":"eng"},{"value":"host","lang":"eng"},{"value":"moderator","lang":"eng"},{"value":"master of ceremonies","lang":"eng"}]}]},{"ent_seq":1306650,"k_ele":[{"keb":"司会者","ke_pri":["news1","nf18"]}],"r_ele":[{"reb":"しかいしゃ","re_pri":["news1","nf18"]}],"sense":[{"pos":["noun (common) (futsuumeishi)"],"gloss":[{"value":"chairman","lang":"eng"},{"value":"moderator","lang":"eng"},{"value":"toastmaster","lang":"eng"},{"value":"master of ceremonies","lang":"eng"},{"value":"chairperson","lang":"eng"},{"value":"host (of a TV show, etc.)","lang":"eng"}]}]},{"ent_seq":1306660,"k_ele":[{"keb":"司教","ke_pri":["news2","nf25"]}],"r_ele":[{"reb":"しきょう","re_pri":["news2","nf25"]}],"sense":[{"pos":["noun (common) (futsuumeishi)"],"xref":["主教"],"gloss":[{"value":"bishop (Catholic)","lang":"eng"}]}]},{"ent_seq":1306670,"k_ele":[{"keb":"司書","ke_pri":["news2","nf32","spec2"]}],"r_ele":[{"reb":"ししょ","re_pri":["news2","nf32","spec2"]}],"sense":[{"pos":["noun (common) (futsuumeishi)"],"gloss":[{"value":"librarian","lang":"eng"}]}]},{"ent_seq":1306680,"k_ele":[{"keb":"司法","ke_pri":["ichi1","news1","nf04"]}],"r_ele":[{"reb":"しほう","re_pri":["ichi1","news1","nf04"]}],"sense":[{"pos":["noun (common) (futsuumeishi)"],"gloss":[{"value":"administration of justice","lang":"eng"},{"value":"judicature","lang":"eng"}]}]},{"ent_seq":1306690,"k_ele":[{"keb":"司法権","ke_pri":["news2","nf29"]}],"r_ele":[{"reb":"しほうけん","re_pri":["news2","nf29"]}],"sense":[{"pos":["noun (common) (futsuumeishi)"],"gloss":[{"value":"judicial power","lang":"eng"},{"value":"jurisdiction","lang":"eng"}]}]},{"ent_seq":1306710,"k_ele":[{"keb":"司令","ke_pri":["news1","nf17"]}],"r_ele":[{"reb":"しれい","re_pri":["news1","nf17"]}],"sense":[{"pos":["noun (common) (futsuumeishi)","noun or participle which takes the aux. verb suru","transitive verb"],"gloss":[{"value":"command","lang":"eng"},{"value":"commander","lang":"eng"},{"value":"commandant","lang":"eng"}]}]},{"ent_seq":1306720,"k_ele":[{"keb":"司令官","ke_pri":["news1","nf03"]}],"r_ele":[{"reb":"しれいかん","re_pri":["news1","nf03"]}],"sense":[{"pos":["noun (common) (futsuumeishi)"],"gloss":[{"value":"commandant","lang":"eng"},{"value":"commanding officer","lang":"eng"},{"value":"general","lang":"eng"}]}]},{"ent_seq":1306740,"k_ele":[{"keb":"司令部","ke_pri":["news1","nf07"]}],"r_ele":[{"reb":"しれいぶ","re_pri":["news1","nf07"]}],"sense":[{"pos":["noun (common) (futsuumeishi)"],"gloss":[{"value":"headquarters","lang":"eng"}]}]},{"ent_seq":1646500,"k_ele":[{"keb":"司直","ke_pri":["news2","nf37"]}],"r_ele":[{"reb":"しちょく","re_pri":["news2","nf37"]}],"sense":[{"pos":["noun (common) (futsuumeishi)"],"gloss":[{"value":"judge","lang":"eng"},{"value":"judiciary","lang":"eng"},{"value":"administration of justice","lang":"eng"},{"value":"judicial authorities","lang":"eng"}]}]},{"ent_seq":1647220,"k_ele":[{"keb":"司祭","ke_pri":["news2","nf28"]}],"r_ele":[{"reb":"しさい","re_pri":["news2","nf28"]}],"sense":[{"pos":["noun (common) (futsuumeishi)","nouns which may take the genitive case particle 'no'"],"gloss":[{"value":"priest","lang":"eng"},{"value":"minister","lang":"eng"},{"value":"pastor","lang":"eng"}]}]},{"ent_seq":1658110,"k_ele":[{"keb":"司法裁判","ke_pri":["news1","nf23"]}],"r_ele":[{"reb":"しほうさいばん","re_pri":["news1","nf23"]}],"sense":[{"pos":["noun (common) (futsuumeishi)"],"gloss":[{"value":"judicial trial","lang":"eng"}]}]},{"ent_seq":1817730,"k_ele":[{"keb":"司法研修所","ke_pri":["news2","nf40"]}],"r_ele":[{"reb":"しほうけんしゅうじょ","re_pri":["news2","nf40"]}],"sense":[{"pos":["noun (common) (futsuumeishi)"],"gloss":[{"value":"Judicial Research and Training Institute","lang":"eng"}]}]},{"ent_seq":1817740,"k_ele":[{"keb":"司法書士","ke_pri":["news2","nf28"]}],"r_ele":[{"reb":"しほうしょし","re_pri":["news2","nf28"]}],"sense":[{"pos":["noun (common) (futsuumeishi)"],"gloss":[{"value":"judicial scrivener","lang":"eng"},{"value":"judicial clerk","lang":"eng"},{"value":"person qualified to prepare legal documents, handle real-estate transactions, etc.","lang":"eng","type":"expl"}]}]}]