[{"ent_seq":1603420,"k_ele":[{"keb":"吠える","ke_pri":["ichi1"]},{"keb":"吼える"},{"keb":"咆える","ke_inf":["rarely used kanji form"]}],"r_ele":[{"reb":"ほえる","re_pri":["ichi1"]}],"sense":[{"pos":["Ichidan verb","intransitive verb"],"gloss":[{"value":"to bark","lang":"eng"},{"value":"to howl","lang":"eng"},{"value":"to bay","lang":"eng"},{"value":"to roar","lang":"eng"},{"value":"to yelp","lang":"eng"},{"value":"to yap","lang":"eng"}]},{"pos":["Ichidan verb","intransitive verb"],"gloss":[{"value":"to howl (of the wind)","lang":"eng"},{"value":"to roar (of the sea)","lang":"eng"}]},{"pos":["Ichidan verb","intransitive verb"],"gloss":[{"value":"to yell","lang":"eng"},{"value":"to shout","lang":"eng"},{"value":"to cry","lang":"eng"},{"value":"to moan","lang":"eng"}]}]}]