[{"ent_seq":1178630,"k_ele":[{"keb":"塩化","ke_pri":["news1","nf18"]}],"r_ele":[{"reb":"えんか","re_pri":["news1","nf18"]}],"sense":[{"pos":["noun (common) (futsuumeishi)","noun or participle which takes the aux. verb suru","intransitive verb"],"field":["chemistry"],"gloss":[{"value":"chloridation","lang":"eng"},{"value":"salification","lang":"eng"}]},{"pos":["noun, used as a prefix"],"xref":["塩化アセチル"],"field":["chemistry"],"gloss":[{"value":"chloride","lang":"eng"}]}]},{"ent_seq":1178640,"k_ele":[{"keb":"塩化ビニール","ke_pri":["news2","nf26"]},{"keb":"塩化ビニル"}],"r_ele":[{"reb":"えんかビニール","re_restr":["塩化ビニール"],"re_pri":["news2","nf26"]},{"reb":"えんかビニル","re_restr":["塩化ビニル"]}],"sense":[{"pos":["noun (common) (futsuumeishi)"],"field":["chemistry"],"gloss":[{"value":"vinyl chloride","lang":"eng"},{"value":"chloroethylene","lang":"eng"}]}]},{"ent_seq":1178680,"k_ele":[{"keb":"塩基","ke_pri":["news1","nf23"]}],"r_ele":[{"reb":"えんき","re_pri":["news1","nf23"]}],"sense":[{"pos":["noun (common) (futsuumeishi)"],"field":["chemistry"],"gloss":[{"value":"base","lang":"eng"}]}]},{"ent_seq":1178710,"k_ele":[{"keb":"塩酸","ke_pri":["news2","nf37","spec2"]}],"r_ele":[{"reb":"えんさん","re_pri":["news2","nf37","spec2"]}],"sense":[{"pos":["noun (common) (futsuumeishi)"],"gloss":[{"value":"hydrochloric acid","lang":"eng"}]}]},{"ent_seq":1178730,"k_ele":[{"keb":"塩焼き","ke_pri":["news2","nf34"]},{"keb":"塩焼"},{"keb":"塩やき","ke_inf":["search-only kanji form"]}],"r_ele":[{"reb":"しおやき","re_pri":["news2","nf34"]}],"sense":[{"pos":["noun (common) (futsuumeishi)","noun or participle which takes the aux. verb suru","transitive verb"],"field":["food, cooking"],"gloss":[{"value":"grilling (fish) with salt","lang":"eng"},{"value":"broiling with salt","lang":"eng"}]},{"pos":["noun (common) (futsuumeishi)","noun or participle which takes the aux. verb suru","transitive verb"],"gloss":[{"value":"boiling seawater to get salt","lang":"eng"}]}]},{"ent_seq":1178740,"k_ele":[{"keb":"塩辛","ke_pri":["news2","nf38"]},{"keb":"塩から"}],"r_ele":[{"reb":"しおから","re_pri":["news2","nf38"]}],"sense":[{"pos":["noun (common) (futsuumeishi)"],"gloss":[{"value":"shiokara","lang":"eng"},{"value":"paste made from salted fermented seafood (squid, fish entrails, etc.)","lang":"eng","type":"expl"}]}]},{"ent_seq":1178750,"k_ele":[{"keb":"塩素","ke_pri":["news1","nf13"]}],"r_ele":[{"reb":"えんそ","re_pri":["news1","nf13"]}],"sense":[{"pos":["noun (common) (futsuumeishi)"],"gloss":[{"value":"chlorine (Cl)","lang":"eng"}]}]},{"ent_seq":1178790,"k_ele":[{"keb":"塩田","ke_pri":["news1","nf24"]}],"r_ele":[{"reb":"えんでん","re_pri":["news1","nf24"]},{"reb":"しおた"},{"reb":"しおだ"}],"sense":[{"pos":["noun (common) (futsuumeishi)"],"gloss":[{"value":"saltpan","lang":"eng"},{"value":"field for drying salt","lang":"eng"}]}]},{"ent_seq":1178870,"k_ele":[{"keb":"塩分","ke_pri":["ichi1","news1","nf15"]}],"r_ele":[{"reb":"えんぶん","re_pri":["ichi1","news1","nf15"]}],"sense":[{"pos":["noun (common) (futsuumeishi)"],"gloss":[{"value":"salt","lang":"eng"},{"value":"salt content","lang":"eng"}]}]},{"ent_seq":1178880,"k_ele":[{"keb":"塩味","ke_pri":["news2","nf37","spec1"]}],"r_ele":[{"reb":"しおあじ","re_pri":["news2","nf37","spec1"]},{"reb":"えんみ"},{"reb":"しおみ"}],"sense":[{"pos":["noun (common) (futsuumeishi)","nouns which may take the genitive case particle 'no'"],"gloss":[{"value":"salty taste","lang":"eng"},{"value":"saltiness","lang":"eng"}]}]},{"ent_seq":1576630,"k_ele":[{"keb":"塩","ke_pri":["ichi1","news1","nf06"]}],"r_ele":[{"reb":"しお","re_pri":["ichi1","news1","nf06"]}],"sense":[{"pos":["noun (common) (futsuumeishi)"],"gloss":[{"value":"salt","lang":"eng"},{"value":"common salt","lang":"eng"},{"value":"table salt","lang":"eng"},{"value":"sodium chloride","lang":"eng"}]},{"pos":["noun (common) (futsuumeishi)"],"gloss":[{"value":"hardship","lang":"eng"},{"value":"toil","lang":"eng"},{"value":"trouble","lang":"eng"}]},{"pos":["noun (common) (futsuumeishi)"],"field":["food, cooking"],"gloss":[{"value":"saltiness","lang":"eng"}]},{"pos":["noun, used as a prefix"],"misc":["colloquial"],"gloss":[{"value":"cold","lang":"eng"},{"value":"unwelcoming","lang":"eng"},{"value":"indifferent","lang":"eng"}]}]},{"ent_seq":1576640,"k_ele":[{"keb":"塩害","ke_pri":["news2","nf38"]}],"r_ele":[{"reb":"えんがい","re_pri":["news2","nf38"]}],"sense":[{"pos":["noun (common) (futsuumeishi)"],"gloss":[{"value":"salt damage (from seawater, sea air, etc.)","lang":"eng"}]}]},{"ent_seq":1576650,"k_ele":[{"keb":"塩水","ke_pri":["ichi1","news2","nf27"]}],"r_ele":[{"reb":"しおみず","re_pri":["ichi1","news2","nf27"]},{"reb":"えんすい"}],"sense":[{"pos":["noun (common) (futsuumeishi)"],"gloss":[{"value":"salt water","lang":"eng"},{"value":"brine","lang":"eng"}]}]},{"ent_seq":1586960,"k_ele":[{"keb":"塩梅","ke_pri":["ichi1"]},{"keb":"按配"},{"keb":"案配","ke_inf":["rarely used kanji form"]},{"keb":"按排","ke_inf":["rarely used kanji form"]},{"keb":"安排","ke_inf":["rarely used kanji form"]}],"r_ele":[{"reb":"あんばい","re_pri":["ichi1"]}],"sense":[{"pos":["noun (common) (futsuumeishi)","noun or participle which takes the aux. verb suru","transitive verb"],"s_inf":["esp. 塩梅"],"gloss":[{"value":"seasoning","lang":"eng"},{"value":"flavour","lang":"eng"},{"value":"flavor","lang":"eng"},{"value":"taste","lang":"eng"}]},{"pos":["noun (common) (futsuumeishi)"],"s_inf":["esp. 塩梅"],"gloss":[{"value":"condition","lang":"eng"},{"value":"state","lang":"eng"},{"value":"situation","lang":"eng"}]},{"pos":["noun (common) (futsuumeishi)"],"s_inf":["esp. 塩梅"],"gloss":[{"value":"(state of) health","lang":"eng"},{"value":"physical condition","lang":"eng"}]},{"pos":["noun (common) (futsuumeishi)","noun or participle which takes the aux. verb suru","transitive verb"],"s_inf":["esp. 按配"],"gloss":[{"value":"arrangement","lang":"eng"},{"value":"assignment","lang":"eng"},{"value":"adjustment","lang":"eng"},{"value":"handling","lang":"eng"},{"value":"dealing with","lang":"eng"}]}]},{"ent_seq":1594080,"k_ele":[{"keb":"塩漬け","ke_pri":["news2","nf30"]},{"keb":"塩漬"},{"keb":"塩づけ","ke_inf":["search-only kanji form"]}],"r_ele":[{"reb":"しおづけ","re_pri":["news2","nf30"]}],"sense":[{"pos":["noun (common) (futsuumeishi)","noun or participle which takes the aux. verb suru","transitive verb"],"gloss":[{"value":"pickling in salt","lang":"eng"},{"value":"food preserved in salt","lang":"eng"}]},{"pos":["noun (common) (futsuumeishi)","nouns which may take the genitive case particle 'no'"],"gloss":[{"value":"holding on to (shares, land, etc.) for an extended period until its value increases","lang":"eng"},{"value":"leaving unsold","lang":"eng"},{"value":"leaving unused","lang":"eng"},{"value":"mothballing","lang":"eng"}]}]},{"ent_seq":1609860,"k_ele":[{"keb":"塩辛い","ke_pri":["ichi1","news2","nf47"]},{"keb":"鹹い","ke_inf":["rarely used kanji form"]}],"r_ele":[{"reb":"しおからい","re_pri":["ichi1","news2","nf47"]},{"reb":"からい","re_restr":["鹹い"]}],"sense":[{"pos":["adjective (keiyoushi)"],"gloss":[{"value":"salty (taste)","lang":"eng"},{"value":"briny","lang":"eng"}]}]},{"ent_seq":1973700,"k_ele":[{"keb":"塩尻","ke_pri":["news2","nf44"]}],"r_ele":[{"reb":"しおじり","re_pri":["news2","nf44"]}],"sense":[{"pos":["noun (common) (futsuumeishi)"],"gloss":[{"value":"cone-shaped","lang":"eng"}]}]}]