[{"ent_seq":1013080,"k_ele":[{"keb":"揺ら揺ら","ke_pri":["ichi1"]}],"r_ele":[{"reb":"ゆらゆら","re_pri":["ichi1"]},{"reb":"ユラユラ","re_nokanji":true}],"sense":[{"pos":["adverb (fukushi)","adverb taking the 'to' particle","noun or participle which takes the aux. verb suru"],"misc":["word usually written using kana alone","onomatopoeic or mimetic word"],"gloss":[{"value":"swaying","lang":"eng"},{"value":"swinging","lang":"eng"},{"value":"rocking","lang":"eng"},{"value":"shaking","lang":"eng"},{"value":"wavering","lang":"eng"},{"value":"flickering","lang":"eng"}]}]},{"ent_seq":1545600,"k_ele":[{"keb":"揺さぶる","ke_pri":["news1","nf23"]},{"keb":"揺さ振る","ke_inf":["rarely used kanji form"]}],"r_ele":[{"reb":"ゆさぶる","re_pri":["news1","nf23"]}],"sense":[{"pos":["Godan verb with 'ru' ending","transitive verb"],"gloss":[{"value":"to shake","lang":"eng"},{"value":"to jolt","lang":"eng"},{"value":"to rock","lang":"eng"},{"value":"to swing","lang":"eng"},{"value":"to sway","lang":"eng"}]},{"pos":["Godan verb with 'ru' ending","transitive verb"],"gloss":[{"value":"to shake (e.g. the political world)","lang":"eng"},{"value":"to disturb","lang":"eng"},{"value":"to shock","lang":"eng"},{"value":"to upset","lang":"eng"}]},{"pos":["Godan verb with 'ru' ending","transitive verb"],"field":["baseball"],"gloss":[{"value":"to put off a batter (by varying one's type of pitch)","lang":"eng"}]}]},{"ent_seq":1545630,"k_ele":[{"keb":"揺らぐ","ke_pri":["ichi1","news1","nf20"]}],"r_ele":[{"reb":"ゆらぐ","re_pri":["ichi1","news1","nf20"]}],"sense":[{"pos":["Godan verb with 'gu' ending","intransitive verb"],"gloss":[{"value":"to swing","lang":"eng"},{"value":"to sway","lang":"eng"},{"value":"to shake","lang":"eng"},{"value":"to tremble","lang":"eng"}]},{"pos":["Godan verb with 'gu' ending","intransitive verb"],"gloss":[{"value":"to waver","lang":"eng"},{"value":"to feel shaken","lang":"eng"},{"value":"to become unstable","lang":"eng"}]}]},{"ent_seq":1545640,"k_ele":[{"keb":"揺らす","ke_pri":["news2","nf40"]}],"r_ele":[{"reb":"ゆらす","re_pri":["news2","nf40"]}],"sense":[{"pos":["Godan verb with 'su' ending","transitive verb"],"gloss":[{"value":"to rock","lang":"eng"},{"value":"to shake","lang":"eng"},{"value":"to swing","lang":"eng"}]}]},{"ent_seq":1545690,"k_ele":[{"keb":"揺るぐ","ke_pri":["news2","nf30","spec2"]}],"r_ele":[{"reb":"ゆるぐ","re_pri":["news2","nf30","spec2"]}],"sense":[{"pos":["Godan verb with 'gu' ending","intransitive verb"],"gloss":[{"value":"to shake","lang":"eng"},{"value":"to waver","lang":"eng"},{"value":"to tremble","lang":"eng"}]}]},{"ent_seq":1545710,"k_ele":[{"keb":"揺れる","ke_pri":["ichi1"]}],"r_ele":[{"reb":"ゆれる","re_pri":["ichi1"]}],"sense":[{"pos":["Ichidan verb","intransitive verb"],"gloss":[{"value":"to shake","lang":"eng"},{"value":"to sway","lang":"eng"},{"value":"to rock","lang":"eng"},{"value":"to swing","lang":"eng"},{"value":"to tremble","lang":"eng"},{"value":"to jolt","lang":"eng"},{"value":"to pitch","lang":"eng"},{"value":"to roll","lang":"eng"},{"value":"to flicker","lang":"eng"}]},{"pos":["Ichidan verb","intransitive verb"],"gloss":[{"value":"to become unstable","lang":"eng"},{"value":"to become unsettled","lang":"eng"},{"value":"to be shaken","lang":"eng"},{"value":"to waver","lang":"eng"}]}]},{"ent_seq":1584980,"k_ele":[{"keb":"揺る","ke_pri":["ichi1","news1","nf19"]},{"keb":"淘る","ke_inf":["word containing out-dated kanji or kanji usage"]},{"keb":"汰る","ke_inf":["word containing out-dated kanji or kanji usage"]}],"r_ele":[{"reb":"ゆる","re_pri":["ichi1","news1","nf19"]}],"sense":[{"pos":["Godan verb with 'ru' ending","transitive verb"],"gloss":[{"value":"to shake","lang":"eng"},{"value":"to jolt","lang":"eng"},{"value":"to rock (cradle)","lang":"eng"},{"value":"to swing","lang":"eng"}]}]},{"ent_seq":1584985,"k_ele":[{"keb":"揺する","ke_pri":["spec2"]}],"r_ele":[{"reb":"ゆする","re_pri":["spec2"]}],"sense":[{"pos":["Godan verb with 'ru' ending","transitive verb"],"gloss":[{"value":"to shake","lang":"eng"},{"value":"to jolt","lang":"eng"},{"value":"to rock (cradle)","lang":"eng"},{"value":"to swing","lang":"eng"}]},{"pos":["Godan verb with 'ru' ending","transitive verb"],"xref":["強請る・ゆする"],"misc":["word usually written using kana alone"],"gloss":[{"value":"to blackmail","lang":"eng"},{"value":"to extort","lang":"eng"},{"value":"to shake down","lang":"eng"}]}]},{"ent_seq":1605770,"k_ele":[{"keb":"揺","ke_pri":["news2","nf27"]},{"keb":"揺り"}],"r_ele":[{"reb":"ゆり","re_pri":["news2","nf27"]}],"sense":[{"pos":["noun (common) (futsuumeishi)"],"gloss":[{"value":"vibration","lang":"eng"},{"value":"flickering","lang":"eng"},{"value":"jolting","lang":"eng"},{"value":"tremor","lang":"eng"}]}]},{"ent_seq":1605780,"k_ele":[{"keb":"揺りかご","ke_pri":["ichi1"]},{"keb":"揺り籠"},{"keb":"揺り篭"},{"keb":"揺籠"},{"keb":"揺篭"},{"keb":"揺り籃"},{"keb":"揺籃"}],"r_ele":[{"reb":"ゆりかご","re_pri":["ichi1"]}],"sense":[{"pos":["noun (common) (futsuumeishi)"],"xref":["揺籃"],"misc":["word usually written using kana alone"],"gloss":[{"value":"cradle","lang":"eng"}]}]},{"ent_seq":1612140,"k_ele":[{"keb":"揺るがす","ke_pri":["ichi1","news1","nf18"]},{"keb":"揺がす","ke_inf":["search-only kanji form"]}],"r_ele":[{"reb":"ゆるがす","re_pri":["ichi1","news1","nf18"]}],"sense":[{"pos":["Godan verb with 'su' ending","transitive verb"],"gloss":[{"value":"to shake","lang":"eng"},{"value":"to swing","lang":"eng"},{"value":"to sway","lang":"eng"},{"value":"to shock","lang":"eng"}]}]},{"ent_seq":1855260,"k_ele":[{"keb":"揺さぶり","ke_pri":["news1","nf15"]},{"keb":"揺さ振り"}],"r_ele":[{"reb":"ゆさぶり","re_pri":["news1","nf15"]}],"sense":[{"pos":["noun (common) (futsuumeishi)"],"gloss":[{"value":"shaking","lang":"eng"},{"value":"jolting","lang":"eng"}]},{"pos":["noun (common) (futsuumeishi)"],"gloss":[{"value":"shaking up (e.g. one's adversary)","lang":"eng"},{"value":"flustering (someone)","lang":"eng"}]}]},{"ent_seq":2112070,"k_ele":[{"keb":"揺らぎ","ke_pri":["spec1"]}],"r_ele":[{"reb":"ゆらぎ","re_pri":["spec1"]}],"sense":[{"pos":["noun (common) (futsuumeishi)"],"gloss":[{"value":"quiver","lang":"eng"},{"value":"quaver","lang":"eng"},{"value":"flutter","lang":"eng"}]},{"pos":["noun (common) (futsuumeishi)"],"field":["statistics"],"gloss":[{"value":"statistical fluctuation","lang":"eng"}]}]}]