[{"ent_seq":1372900,"k_ele":[{"keb":"数える","ke_pri":["ichi1","news1","nf17"]},{"keb":"算える","ke_inf":["rarely used kanji form"]}],"r_ele":[{"reb":"かぞえる","re_pri":["ichi1","news1","nf17"]}],"sense":[{"pos":["Ichidan verb","transitive verb"],"gloss":[{"value":"to count","lang":"eng"},{"value":"to enumerate","lang":"eng"}]}]},{"ent_seq":1372930,"k_ele":[{"keb":"数え切れない","ke_pri":["news2","nf28"]},{"keb":"数えきれない"}],"r_ele":[{"reb":"かぞえきれない","re_pri":["news2","nf28"]}],"sense":[{"pos":["adjective (keiyoushi)"],"gloss":[{"value":"countless","lang":"eng"},{"value":"incalculable","lang":"eng"}]}]},{"ent_seq":1372960,"k_ele":[{"keb":"数億年","ke_pri":["news1","nf15"]}],"r_ele":[{"reb":"すうおくねん","re_pri":["news1","nf15"]}],"sense":[{"pos":["noun (common) (futsuumeishi)"],"gloss":[{"value":"several hundred million years","lang":"eng"}]}]},{"ent_seq":1372970,"k_ele":[{"keb":"数回","ke_pri":["spec1"]}],"r_ele":[{"reb":"すうかい","re_pri":["spec1"]}],"sense":[{"pos":["noun (common) (futsuumeishi)"],"gloss":[{"value":"several times","lang":"eng"},{"value":"a few times","lang":"eng"}]}]},{"ent_seq":1372980,"k_ele":[{"keb":"数学","ke_pri":["ichi1","news1","nf09"]}],"r_ele":[{"reb":"すうがく","re_pri":["ichi1","news1","nf09"]}],"sense":[{"pos":["noun (common) (futsuumeishi)"],"gloss":[{"value":"mathematics","lang":"eng"}]}]},{"ent_seq":1373000,"k_ele":[{"keb":"数奇","ke_pri":["news2","nf31"]}],"r_ele":[{"reb":"すうき","re_pri":["news2","nf31"]},{"reb":"さっき"}],"sense":[{"pos":["noun (common) (futsuumeishi)","adjectival nouns or quasi-adjectives (keiyodoshi)"],"gloss":[{"value":"misfortune","lang":"eng"},{"value":"adverse fortune","lang":"eng"},{"value":"hapless fate","lang":"eng"}]},{"pos":["adjectival nouns or quasi-adjectives (keiyodoshi)","noun (common) (futsuumeishi)"],"gloss":[{"value":"checkered (life, career, etc.)","lang":"eng"},{"value":"varied","lang":"eng"},{"value":"eventful","lang":"eng"},{"value":"dramatic","lang":"eng"},{"value":"full of ups and downs","lang":"eng"}]}]},{"ent_seq":1373010,"k_ele":[{"keb":"数寄","ke_inf":["ateji (phonetic) reading"],"ke_pri":["news2","nf28"]},{"keb":"数奇","ke_inf":["ateji (phonetic) reading"]}],"r_ele":[{"reb":"すき","re_pri":["news2","nf28"]}],"sense":[{"pos":["noun (common) (futsuumeishi)"],"gloss":[{"value":"refined taste","lang":"eng"},{"value":"elegant pursuits","lang":"eng"}]}]},{"ent_seq":1373030,"k_ele":[{"keb":"数個","ke_pri":["news1","nf23"]}],"r_ele":[{"reb":"すうこ","re_pri":["news1","nf23"]}],"sense":[{"pos":["noun (common) (futsuumeishi)"],"gloss":[{"value":"several (objects, usu. from two to six)","lang":"eng"}]}]},{"ent_seq":1373060,"k_ele":[{"keb":"数字","ke_pri":["ichi1","news1","nf02"]}],"r_ele":[{"reb":"すうじ","re_pri":["ichi1","news1","nf02"]}],"sense":[{"pos":["noun (common) (futsuumeishi)"],"gloss":[{"value":"numeral","lang":"eng"},{"value":"digit","lang":"eng"},{"value":"numeric character","lang":"eng"}]},{"pos":["noun (common) (futsuumeishi)"],"gloss":[{"value":"figure","lang":"eng"},{"value":"number","lang":"eng"}]},{"pos":["noun (common) (futsuumeishi)"],"gloss":[{"value":"a few characters","lang":"eng"}]}]},{"ent_seq":1373070,"k_ele":[{"keb":"数式","ke_pri":["news2","nf34"]}],"r_ele":[{"reb":"すうしき","re_pri":["news2","nf34"]}],"sense":[{"pos":["noun (common) (futsuumeishi)"],"gloss":[{"value":"numerical formula","lang":"eng"}]}]},{"ent_seq":1373080,"k_ele":[{"keb":"数珠","ke_pri":["news2","nf30","spec2"]},{"keb":"珠数","ke_inf":["rarely used kanji form"]}],"r_ele":[{"reb":"じゅず","re_pri":["news2","nf30","spec2"]},{"reb":"ずず"}],"sense":[{"pos":["noun (common) (futsuumeishi)"],"field":["Buddhism"],"gloss":[{"value":"rosary","lang":"eng"},{"value":"string of prayer beads","lang":"eng"}]}]},{"ent_seq":1373090,"k_ele":[{"keb":"数人","ke_pri":["spec1"]}],"r_ele":[{"reb":"すうにん","re_pri":["spec1"]}],"sense":[{"pos":["noun (common) (futsuumeishi)"],"gloss":[{"value":"several people","lang":"eng"},{"value":"a few people","lang":"eng"}]}]},{"ent_seq":1373120,"k_ele":[{"keb":"数千","ke_pri":["news2","nf33","spec1"]}],"r_ele":[{"reb":"すうせん","re_pri":["news2","nf33","spec1"]}],"sense":[{"pos":["noun (common) (futsuumeishi)"],"gloss":[{"value":"thousands","lang":"eng"},{"value":"several thousand","lang":"eng"}]}]},{"ent_seq":1373150,"k_ele":[{"keb":"数多く","ke_pri":["news1","nf09"]}],"r_ele":[{"reb":"かずおおく","re_pri":["news1","nf09"]}],"sense":[{"pos":["expressions (phrases, clauses, etc.)","adverb (fukushi)","nouns which may take the genitive case particle 'no'"],"gloss":[{"value":"in great numbers","lang":"eng"}]}]},{"ent_seq":1373160,"k_ele":[{"keb":"数値","ke_pri":["ichi1","news1","nf05"]}],"r_ele":[{"reb":"すうち","re_pri":["ichi1","news1","nf05"]}],"sense":[{"pos":["noun (common) (futsuumeishi)"],"gloss":[{"value":"numerical value","lang":"eng"}]},{"pos":["noun (common) (futsuumeishi)"],"gloss":[{"value":"figure","lang":"eng"},{"value":"result","lang":"eng"},{"value":"reading (on a meter, etc.)","lang":"eng"}]}]},{"ent_seq":1373200,"k_ele":[{"keb":"数日","ke_pri":["news1","nf08"]}],"r_ele":[{"reb":"すうじつ","re_pri":["news1","nf08"]}],"sense":[{"pos":["noun (common) (futsuumeishi)"],"gloss":[{"value":"few days","lang":"eng"}]}]},{"ent_seq":1373230,"k_ele":[{"keb":"数年","ke_pri":["spec1"]}],"r_ele":[{"reb":"すうねん","re_pri":["spec1"]}],"sense":[{"pos":["noun (common) (futsuumeishi)"],"gloss":[{"value":"several years","lang":"eng"},{"value":"a few years","lang":"eng"}]}]},{"ent_seq":1373250,"k_ele":[{"keb":"数百","ke_pri":["news1","nf07"]}],"r_ele":[{"reb":"すうひゃく","re_pri":["news1","nf07"]}],"sense":[{"pos":["noun (common) (futsuumeishi)"],"gloss":[{"value":"several hundred","lang":"eng"},{"value":"hundreds (of)","lang":"eng"}]}]},{"ent_seq":1373300,"k_ele":[{"keb":"数理","ke_pri":["news2","nf30"]}],"r_ele":[{"reb":"すうり","re_pri":["news2","nf30"]}],"sense":[{"pos":["noun (common) (futsuumeishi)"],"gloss":[{"value":"mathematical principle","lang":"eng"},{"value":"mathematics","lang":"eng"}]},{"pos":["noun (common) (futsuumeishi)"],"gloss":[{"value":"arithmetic","lang":"eng"},{"value":"figures","lang":"eng"},{"value":"accounts","lang":"eng"}]}]},{"ent_seq":1373320,"k_ele":[{"keb":"数量","ke_pri":["ichi1","news1","nf07"]}],"r_ele":[{"reb":"すうりょう","re_pri":["ichi1","news1","nf07"]}],"sense":[{"pos":["noun (common) (futsuumeishi)"],"gloss":[{"value":"quantity","lang":"eng"},{"value":"volume","lang":"eng"},{"value":"amount","lang":"eng"}]}]},{"ent_seq":1580820,"k_ele":[{"keb":"数","ke_pri":["ichi1","news1","nf02"]}],"r_ele":[{"reb":"かず","re_pri":["ichi1","news1","nf02"]}],"sense":[{"pos":["noun (common) (futsuumeishi)"],"gloss":[{"value":"number","lang":"eng"},{"value":"amount","lang":"eng"}]}]},{"ent_seq":1580825,"k_ele":[{"keb":"数","ke_pri":["ichi1"]}],"r_ele":[{"reb":"すう","re_pri":["ichi1"]}],"sense":[{"pos":["prefix"],"gloss":[{"value":"several","lang":"eng"},{"value":"a few","lang":"eng"},{"value":"a number of","lang":"eng"}]},{"pos":["noun (common) (futsuumeishi)","noun, used as a suffix"],"gloss":[{"value":"number","lang":"eng"},{"value":"quantity","lang":"eng"},{"value":"amount","lang":"eng"}]},{"pos":["noun (common) (futsuumeishi)"],"gloss":[{"value":"counting","lang":"eng"},{"value":"calculation","lang":"eng"},{"value":"figures","lang":"eng"},{"value":"numbers","lang":"eng"}]},{"pos":["noun (common) (futsuumeishi)"],"gloss":[{"value":"number","lang":"eng"},{"value":"numeral","lang":"eng"},{"value":"figure","lang":"eng"}]},{"pos":["noun (common) (futsuumeishi)"],"field":["grammar"],"gloss":[{"value":"number","lang":"eng"}]},{"pos":["noun (common) (futsuumeishi)"],"gloss":[{"value":"destiny","lang":"eng"},{"value":"fate","lang":"eng"},{"value":"outcome","lang":"eng"},{"value":"course of events","lang":"eng"},{"value":"trend","lang":"eng"}]}]},{"ent_seq":1590300,"k_ele":[{"keb":"数々","ke_pri":["news1","nf07"]},{"keb":"数数"}],"r_ele":[{"reb":"かずかず","re_pri":["news1","nf07"]}],"sense":[{"pos":["noun (common) (futsuumeishi)","nouns which may take the genitive case particle 'no'","adverb (fukushi)"],"xref":["数々・しばしば"],"gloss":[{"value":"many","lang":"eng"},{"value":"numerous","lang":"eng"},{"value":"various","lang":"eng"},{"value":"large number of","lang":"eng"}]}]},{"ent_seq":1595540,"k_ele":[{"keb":"数ヶ月","ke_pri":["spec1"]},{"keb":"数カ月"},{"keb":"数ヵ月"},{"keb":"数か月"},{"keb":"数ケ月"},{"keb":"数箇月"}],"r_ele":[{"reb":"すうかげつ","re_pri":["spec1"]}],"sense":[{"pos":["noun (common) (futsuumeishi)"],"gloss":[{"value":"several months","lang":"eng"}]}]},{"ent_seq":1709220,"k_ele":[{"keb":"数十","ke_pri":["news2","nf29","spec1"]}],"r_ele":[{"reb":"すうじゅう","re_pri":["news2","nf29","spec1"]}],"sense":[{"pos":["noun (common) (futsuumeishi)","nouns which may take the genitive case particle 'no'"],"gloss":[{"value":"dozens","lang":"eng"},{"value":"scores of","lang":"eng"},{"value":"decades","lang":"eng"}]}]},{"ent_seq":1709230,"k_ele":[{"keb":"数万","ke_pri":["news1","nf10"]}],"r_ele":[{"reb":"すうまん","re_pri":["news1","nf10"]}],"sense":[{"pos":["noun (common) (futsuumeishi)","nouns which may take the genitive case particle 'no'"],"gloss":[{"value":"tens of thousands","lang":"eng"}]}]},{"ent_seq":1709250,"k_ele":[{"keb":"数次","ke_pri":["news1","nf13"]}],"r_ele":[{"reb":"すうじ","re_pri":["news1","nf13"]}],"sense":[{"pos":["noun (common) (futsuumeishi)"],"gloss":[{"value":"several times","lang":"eng"}]}]},{"ent_seq":2011730,"k_ele":[{"keb":"数少ない","ke_pri":["spec1"]}],"r_ele":[{"reb":"かずすくない","re_pri":["spec1"]}],"sense":[{"pos":["adjective (keiyoushi)"],"gloss":[{"value":"few in number","lang":"eng"}]}]},{"ent_seq":2182740,"k_ele":[{"keb":"数時間","ke_pri":["spec1"]}],"r_ele":[{"reb":"すうじかん","re_pri":["spec1"]}],"sense":[{"pos":["noun (common) (futsuumeishi)"],"gloss":[{"value":"a few hours","lang":"eng"},{"value":"several hours","lang":"eng"},{"value":"a couple of hours","lang":"eng"}]}]},{"ent_seq":2182750,"k_ele":[{"keb":"数分","ke_pri":["spec1"]}],"r_ele":[{"reb":"すうふん","re_pri":["spec1"]}],"sense":[{"pos":["noun (common) (futsuumeishi)"],"gloss":[{"value":"several minutes","lang":"eng"},{"value":"a few minutes","lang":"eng"}]}]},{"ent_seq":2654980,"k_ele":[{"keb":"数年前","ke_pri":["spec1"]}],"r_ele":[{"reb":"すうねんまえ","re_pri":["spec1"]}],"sense":[{"pos":["adverb (fukushi)","nouns which may take the genitive case particle 'no'"],"gloss":[{"value":"a few years ago","lang":"eng"},{"value":"some years back","lang":"eng"}]}]}]