[{"ent_seq":1519610,"k_ele":[{"keb":"望ましい","ke_pri":["ichi1","news1","nf19"]}],"r_ele":[{"reb":"のぞましい","re_pri":["ichi1","news1","nf19"]}],"sense":[{"pos":["adjective (keiyoushi)"],"gloss":[{"value":"desirable","lang":"eng"},{"value":"hoped for","lang":"eng"},{"value":"preferable","lang":"eng"},{"value":"advisable","lang":"eng"}]}]},{"ent_seq":1519620,"k_ele":[{"keb":"望み","ke_pri":["ichi1","news1","nf10"]}],"r_ele":[{"reb":"のぞみ","re_pri":["ichi1","news1","nf10"]}],"sense":[{"pos":["noun (common) (futsuumeishi)"],"gloss":[{"value":"wish","lang":"eng"},{"value":"desire","lang":"eng"},{"value":"hope","lang":"eng"}]},{"pos":["noun (common) (futsuumeishi)"],"gloss":[{"value":"prospect","lang":"eng"},{"value":"expectation","lang":"eng"},{"value":"(one's) hopes","lang":"eng"}]}]},{"ent_seq":1519630,"k_ele":[{"keb":"望む","ke_pri":["ichi1","news1","nf12"]}],"r_ele":[{"reb":"のぞむ","re_pri":["ichi1","news1","nf12"]}],"sense":[{"pos":["Godan verb with 'mu' ending","transitive verb"],"gloss":[{"value":"to desire","lang":"eng"},{"value":"to want","lang":"eng"},{"value":"to wish for","lang":"eng"},{"value":"to hope for","lang":"eng"}]},{"pos":["Godan verb with 'mu' ending","transitive verb"],"gloss":[{"value":"to expect (of someone)","lang":"eng"},{"value":"to hope for","lang":"eng"},{"value":"to look forward to","lang":"eng"}]},{"pos":["Godan verb with 'mu' ending","transitive verb"],"gloss":[{"value":"to see","lang":"eng"},{"value":"to command (a view of)","lang":"eng"},{"value":"to overlook","lang":"eng"}]}]},{"ent_seq":1519640,"k_ele":[{"keb":"望遠","ke_pri":["news2","nf31"]}],"r_ele":[{"reb":"ぼうえん","re_pri":["news2","nf31"]}],"sense":[{"pos":["noun (common) (futsuumeishi)"],"gloss":[{"value":"seeing at a distance","lang":"eng"}]}]},{"ent_seq":1519650,"k_ele":[{"keb":"望遠鏡","ke_pri":["ichi1","news1","nf13"]}],"r_ele":[{"reb":"ぼうえんきょう","re_pri":["ichi1","news1","nf13"]}],"sense":[{"pos":["noun (common) (futsuumeishi)"],"gloss":[{"value":"telescope","lang":"eng"}]}]},{"ent_seq":1519660,"k_ele":[{"keb":"望郷","ke_pri":["news2","nf25"]}],"r_ele":[{"reb":"ぼうきょう","re_pri":["news2","nf25"]}],"sense":[{"pos":["noun (common) (futsuumeishi)"],"gloss":[{"value":"homesickness","lang":"eng"},{"value":"nostalgia","lang":"eng"}]}]},{"ent_seq":1519680,"k_ele":[{"keb":"望月","ke_pri":["news1","nf11"]},{"keb":"もち月","ke_inf":["search-only kanji form"]}],"r_ele":[{"reb":"もちづき","re_pri":["news1","nf11"]},{"reb":"ぼうげつ"}],"sense":[{"pos":["noun (common) (futsuumeishi)"],"gloss":[{"value":"full moon","lang":"eng"},{"value":"moon on the 15th day of the month (by the lunar calendar)","lang":"eng"}]},{"stagr":["もちづき"],"pos":["noun (common) (futsuumeishi)"],"gloss":[{"value":"full moon of the eighth lunar month","lang":"eng"}]}]},{"ent_seq":1620320,"k_ele":[{"keb":"望外","ke_pri":["news2","nf40"]}],"r_ele":[{"reb":"ぼうがい","re_pri":["news2","nf40"]}],"sense":[{"pos":["nouns which may take the genitive case particle 'no'","adjectival nouns or quasi-adjectives (keiyodoshi)","noun (common) (futsuumeishi)"],"gloss":[{"value":"unexpected (joy, success, etc.)","lang":"eng"},{"value":"unanticipated","lang":"eng"},{"value":"beyond what one hoped","lang":"eng"},{"value":"beyond one's expectations","lang":"eng"}]}]}]