[{"ent_seq":1349860,"k_ele":[{"keb":"松","ke_pri":["ichi1","news1","nf04"]}],"r_ele":[{"reb":"まつ","re_pri":["ichi1","news1","nf04"]},{"reb":"マツ","re_nokanji":true}],"sense":[{"pos":["noun (common) (futsuumeishi)"],"gloss":[{"value":"pine tree (Pinus spp.)","lang":"eng"}]},{"pos":["noun (common) (futsuumeishi)"],"xref":["梅・うめ・2","竹・たけ・2"],"gloss":[{"value":"highest (of a three-tier ranking system)","lang":"eng"}]}]},{"ent_seq":1349920,"k_ele":[{"keb":"松竹梅","ke_pri":["news2","nf47"]}],"r_ele":[{"reb":"しょうちくばい","re_pri":["news2","nf47"]}],"sense":[{"pos":["noun (common) (futsuumeishi)"],"xref":["歳寒三友"],"gloss":[{"value":"pine, bamboo and plum (an auspicious grouping)","lang":"eng"}]},{"pos":["noun (common) (futsuumeishi)"],"s_inf":["from 松 down to 梅"],"gloss":[{"value":"high, middle and low (ranking)","lang":"eng"},{"value":"top, middle and bottom","lang":"eng"},{"value":"upper, medium, lower","lang":"eng"},{"value":"first, second and third (class)","lang":"eng"}]}]},{"ent_seq":1349950,"k_ele":[{"keb":"松葉","ke_pri":["news1","nf21"]}],"r_ele":[{"reb":"まつば","re_pri":["news1","nf21"]}],"sense":[{"pos":["noun (common) (futsuumeishi)"],"gloss":[{"value":"pine needle","lang":"eng"}]}]},{"ent_seq":1349970,"k_ele":[{"keb":"松林","ke_pri":["news2","nf28","spec2"]}],"r_ele":[{"reb":"まつばやし","re_pri":["news2","nf28","spec2"]}],"sense":[{"pos":["noun (common) (futsuumeishi)"],"gloss":[{"value":"pine forest","lang":"eng"}]}]},{"ent_seq":1632080,"k_ele":[{"keb":"松明","ke_pri":["news2","nf35"]},{"keb":"炬","ke_inf":["rarely used kanji form"]}],"r_ele":[{"reb":"たいまつ","re_inf":["gikun (meaning as reading) or jukujikun (special kanji reading)"],"re_pri":["news2","nf35"]},{"reb":"しょうめい","re_restr":["松明"]}],"sense":[{"pos":["noun (common) (futsuumeishi)"],"gloss":[{"value":"torch (made of pine, bamboo, reed, etc.)","lang":"eng"},{"value":"flambeau","lang":"eng"},{"value":"torchlight","lang":"eng"}]}]},{"ent_seq":1649470,"k_ele":[{"keb":"松風","ke_pri":["news2","nf38"]}],"r_ele":[{"reb":"まつかぜ"},{"reb":"しょうふう","re_pri":["news2","nf38"]}],"sense":[{"pos":["noun (common) (futsuumeishi)"],"gloss":[{"value":"(sound of) wind blowing through pine trees","lang":"eng"}]},{"stagr":["まつかぜ"],"pos":["noun (common) (futsuumeishi)"],"gloss":[{"value":"(sound of) steam whistling in a kettle (at a tea ceremony)","lang":"eng"}]},{"stagr":["まつかぜ"],"pos":["noun (common) (futsuumeishi)"],"gloss":[{"value":"matsukaze","lang":"eng"},{"value":"sugar-glazed cookie sprinkled with sesame or poppy seeds","lang":"eng","type":"expl"}]}]}]