[{"ent_seq":1281000,"k_ele":[{"keb":"考え","ke_pri":["ichi1","news1","nf01"]}],"r_ele":[{"reb":"かんがえ","re_pri":["ichi1","news1","nf01"]}],"sense":[{"pos":["noun (common) (futsuumeishi)"],"gloss":[{"value":"thinking","lang":"eng"},{"value":"thought","lang":"eng"},{"value":"view","lang":"eng"},{"value":"opinion","lang":"eng"},{"value":"concept","lang":"eng"}]},{"pos":["noun (common) (futsuumeishi)"],"gloss":[{"value":"idea","lang":"eng"},{"value":"notion","lang":"eng"},{"value":"imagination","lang":"eng"}]},{"pos":["noun (common) (futsuumeishi)"],"gloss":[{"value":"intention","lang":"eng"},{"value":"plan","lang":"eng"},{"value":"design","lang":"eng"}]},{"pos":["noun (common) (futsuumeishi)"],"gloss":[{"value":"consideration","lang":"eng"},{"value":"judgement","lang":"eng"},{"value":"deliberation","lang":"eng"},{"value":"reflection","lang":"eng"}]},{"pos":["noun (common) (futsuumeishi)"],"gloss":[{"value":"wish","lang":"eng"},{"value":"hope","lang":"eng"},{"value":"expectation","lang":"eng"}]}]},{"ent_seq":1281010,"k_ele":[{"keb":"考えてみれば","ke_pri":["spec1"]},{"keb":"考えて見れば"}],"r_ele":[{"reb":"かんがえてみれば","re_pri":["spec1"]}],"sense":[{"pos":["expressions (phrases, clauses, etc.)"],"gloss":[{"value":"if you think about it","lang":"eng"},{"value":"come to think of it","lang":"eng"}]}]},{"ent_seq":1281020,"k_ele":[{"keb":"考える","ke_pri":["ichi1","news1","nf10"]},{"keb":"勘える"},{"keb":"稽える"}],"r_ele":[{"reb":"かんがえる","re_pri":["ichi1","news1","nf10"]}],"sense":[{"pos":["Ichidan verb","transitive verb"],"gloss":[{"value":"to think (about, of)","lang":"eng"},{"value":"to think over","lang":"eng"},{"value":"to ponder","lang":"eng"},{"value":"to contemplate","lang":"eng"},{"value":"to reflect (on)","lang":"eng"},{"value":"to meditate (on)","lang":"eng"}]},{"pos":["Ichidan verb","transitive verb"],"gloss":[{"value":"to consider","lang":"eng"},{"value":"to bear in mind","lang":"eng"},{"value":"to allow for","lang":"eng"},{"value":"to take into consideration","lang":"eng"}]},{"pos":["Ichidan verb","transitive verb"],"gloss":[{"value":"to think (that)","lang":"eng"},{"value":"to believe","lang":"eng"},{"value":"to hold (a view)","lang":"eng"},{"value":"to judge","lang":"eng"},{"value":"to conclude","lang":"eng"},{"value":"to suspect","lang":"eng"}]},{"pos":["Ichidan verb","transitive verb"],"gloss":[{"value":"to intend (to do)","lang":"eng"},{"value":"to think of (doing)","lang":"eng"},{"value":"to plan","lang":"eng"}]},{"pos":["Ichidan verb","transitive verb"],"gloss":[{"value":"to predict","lang":"eng"},{"value":"to anticipate","lang":"eng"},{"value":"to expect","lang":"eng"},{"value":"to imagine","lang":"eng"}]},{"pos":["Ichidan verb","transitive verb"],"gloss":[{"value":"to come up with","lang":"eng"},{"value":"to think up","lang":"eng"},{"value":"to contrive","lang":"eng"},{"value":"to devise","lang":"eng"}]},{"pos":["Ichidan verb","transitive verb"],"gloss":[{"value":"to consider (as)","lang":"eng"},{"value":"to regard (as)","lang":"eng"},{"value":"to look on (as)","lang":"eng"},{"value":"to take","lang":"eng"},{"value":"to view","lang":"eng"}]}]},{"ent_seq":1281030,"k_ele":[{"keb":"考え込む","ke_pri":["news2","nf30"]},{"keb":"考えこむ"}],"r_ele":[{"reb":"かんがえこむ","re_pri":["news2","nf30"]}],"sense":[{"pos":["Godan verb with 'mu' ending","intransitive verb"],"gloss":[{"value":"to ponder","lang":"eng"},{"value":"to brood","lang":"eng"}]}]},{"ent_seq":1281050,"k_ele":[{"keb":"考え出す","ke_pri":["news2","nf38"]},{"keb":"考えだす"}],"r_ele":[{"reb":"かんがえだす","re_pri":["news2","nf38"]}],"sense":[{"pos":["Godan verb with 'su' ending","transitive verb"],"gloss":[{"value":"to think out","lang":"eng"},{"value":"to devise","lang":"eng"},{"value":"to invent","lang":"eng"},{"value":"to begin to think","lang":"eng"},{"value":"to come up with a plan","lang":"eng"}]}]},{"ent_seq":1281070,"k_ele":[{"keb":"考え直す","ke_pri":["spec1"]},{"keb":"考えなおす"}],"r_ele":[{"reb":"かんがえなおす","re_pri":["spec1"]}],"sense":[{"pos":["Godan verb with 'su' ending","transitive verb"],"gloss":[{"value":"to reconsider","lang":"eng"},{"value":"to rethink","lang":"eng"},{"value":"to reassess","lang":"eng"}]}]},{"ent_seq":1281090,"k_ele":[{"keb":"考え方","ke_pri":["news1","nf02"]}],"r_ele":[{"reb":"かんがえかた","re_pri":["news1","nf02"]}],"sense":[{"pos":["noun (common) (futsuumeishi)"],"gloss":[{"value":"way of thinking","lang":"eng"},{"value":"point of view","lang":"eng"},{"value":"opinion","lang":"eng"},{"value":"approach (e.g. to a problem)","lang":"eng"},{"value":"attitude","lang":"eng"}]}]},{"ent_seq":1281100,"k_ele":[{"keb":"考案","ke_pri":["news2","nf33","spec2"]},{"keb":"考按","ke_inf":["rarely used kanji form"]}],"r_ele":[{"reb":"こうあん","re_pri":["news2","nf33","spec2"]}],"sense":[{"pos":["noun (common) (futsuumeishi)","noun or participle which takes the aux. verb suru","transitive verb"],"gloss":[{"value":"plan","lang":"eng"},{"value":"device","lang":"eng"},{"value":"idea","lang":"eng"},{"value":"design","lang":"eng"},{"value":"contrivance","lang":"eng"},{"value":"conception","lang":"eng"},{"value":"invention","lang":"eng"}]}]},{"ent_seq":1281120,"k_ele":[{"keb":"考古学","ke_pri":["news1","nf10"]}],"r_ele":[{"reb":"こうこがく","re_pri":["news1","nf10"]}],"sense":[{"pos":["noun (common) (futsuumeishi)","nouns which may take the genitive case particle 'no'"],"gloss":[{"value":"archaeology","lang":"eng"},{"value":"archeology","lang":"eng"}]}]},{"ent_seq":1281140,"k_ele":[{"keb":"考査","ke_pri":["news2","nf26"]}],"r_ele":[{"reb":"こうさ","re_pri":["news2","nf26"]}],"sense":[{"pos":["noun (common) (futsuumeishi)","noun or participle which takes the aux. verb suru","transitive verb"],"gloss":[{"value":"examination","lang":"eng"},{"value":"consideration","lang":"eng"},{"value":"test","lang":"eng"},{"value":"quiz","lang":"eng"}]}]},{"ent_seq":1281150,"k_ele":[{"keb":"考察","ke_pri":["news1","nf21"]}],"r_ele":[{"reb":"こうさつ","re_pri":["news1","nf21"]}],"sense":[{"pos":["noun (common) (futsuumeishi)","noun or participle which takes the aux. verb suru","transitive verb"],"gloss":[{"value":"consideration","lang":"eng"},{"value":"inquiry","lang":"eng"},{"value":"enquiry","lang":"eng"},{"value":"investigation","lang":"eng"},{"value":"study","lang":"eng"}]}]},{"ent_seq":1281160,"k_ele":[{"keb":"考証","ke_pri":["news2","nf30","spec2"]}],"r_ele":[{"reb":"こうしょう","re_pri":["news2","nf30","spec2"]}],"sense":[{"pos":["noun (common) (futsuumeishi)","noun or participle which takes the aux. verb suru","transitive verb"],"gloss":[{"value":"investigation into historical evidence","lang":"eng"},{"value":"study of historical artifacts","lang":"eng"}]}]},{"ent_seq":1281170,"k_ele":[{"keb":"考慮","ke_pri":["ichi1","news1","nf12"]}],"r_ele":[{"reb":"こうりょ","re_pri":["ichi1","news1","nf12"]}],"sense":[{"pos":["noun (common) (futsuumeishi)","noun or participle which takes the aux. verb suru","transitive verb"],"gloss":[{"value":"consideration","lang":"eng"},{"value":"taking into account","lang":"eng"}]}]}]