[{"ent_seq":1232630,"k_ele":[{"keb":"虚々実々","ke_pri":["news2","nf39"]},{"keb":"虚虚実実"}],"r_ele":[{"reb":"きょきょじつじつ","re_pri":["news2","nf39"]}],"sense":[{"pos":["noun (common) (futsuumeishi)","nouns which may take the genitive case particle 'no'"],"misc":["yojijukugo"],"gloss":[{"value":"full of wiles and tricks","lang":"eng"},{"value":"match between persons equal in shrewdness mobilizing all the tricks each can muster","lang":"eng"},{"value":"shrewdly avoiding the opponent's strong points and attacking its weaknesses","lang":"eng"}]}]},{"ent_seq":1232660,"k_ele":[{"keb":"虚栄","ke_pri":["news2","nf45","spec2"]}],"r_ele":[{"reb":"きょえい","re_pri":["news2","nf45","spec2"]}],"sense":[{"pos":["noun (common) (futsuumeishi)"],"gloss":[{"value":"vanity","lang":"eng"},{"value":"vainglory","lang":"eng"}]}]},{"ent_seq":1232670,"k_ele":[{"keb":"虚偽","ke_pri":["news1","nf08"]}],"r_ele":[{"reb":"きょぎ","re_pri":["news1","nf08"]},{"reb":"こぎ","re_inf":["out-dated or obsolete kana usage"]}],"sense":[{"pos":["noun (common) (futsuumeishi)","nouns which may take the genitive case particle 'no'"],"gloss":[{"value":"falsehood","lang":"eng"},{"value":"untruth","lang":"eng"},{"value":"lie","lang":"eng"},{"value":"misinformation","lang":"eng"}]},{"pos":["noun (common) (futsuumeishi)"],"field":["logic"],"gloss":[{"value":"fallacy","lang":"eng"}]}]},{"ent_seq":1232680,"k_ele":[{"keb":"虚空","ke_pri":["news2","nf45","spec2"]}],"r_ele":[{"reb":"こくう","re_pri":["news2","nf45","spec2"]}],"sense":[{"pos":["noun (common) (futsuumeishi)"],"gloss":[{"value":"empty space","lang":"eng"},{"value":"empty sky","lang":"eng"}]}]},{"ent_seq":1232700,"k_ele":[{"keb":"虚言","ke_pri":["news2","nf47"]}],"r_ele":[{"reb":"きょげん","re_pri":["news2","nf47"]},{"reb":"きょごん"}],"sense":[{"pos":["noun (common) (futsuumeishi)"],"gloss":[{"value":"falsehood","lang":"eng"},{"value":"lie","lang":"eng"}]}]},{"ent_seq":1232710,"k_ele":[{"keb":"虚構","ke_pri":["ichi1","news1","nf20"]}],"r_ele":[{"reb":"きょこう","re_pri":["ichi1","news1","nf20"]}],"sense":[{"pos":["noun (common) (futsuumeishi)","noun or participle which takes the aux. verb suru","transitive verb","nouns which may take the genitive case particle 'no'"],"gloss":[{"value":"fiction","lang":"eng"},{"value":"fabrication","lang":"eng"},{"value":"concoction","lang":"eng"}]}]},{"ent_seq":1232720,"k_ele":[{"keb":"虚弱","ke_pri":["news2","nf39","spec2"]}],"r_ele":[{"reb":"きょじゃく","re_pri":["news2","nf39","spec2"]}],"sense":[{"pos":["adjectival nouns or quasi-adjectives (keiyodoshi)","nouns which may take the genitive case particle 'no'","noun (common) (futsuumeishi)"],"gloss":[{"value":"feebleness","lang":"eng"},{"value":"weakness","lang":"eng"},{"value":"imbecility","lang":"eng"}]}]},{"ent_seq":1232730,"k_ele":[{"keb":"虚飾","ke_pri":["news2","nf39"]}],"r_ele":[{"reb":"きょしょく","re_pri":["news2","nf39"]}],"sense":[{"pos":["noun (common) (futsuumeishi)","nouns which may take the genitive case particle 'no'"],"gloss":[{"value":"ostentation","lang":"eng"},{"value":"show","lang":"eng"},{"value":"affectation","lang":"eng"}]}]},{"ent_seq":1232740,"k_ele":[{"keb":"虚心","ke_pri":["news2","nf43","spec2"]}],"r_ele":[{"reb":"きょしん","re_pri":["news2","nf43","spec2"]}],"sense":[{"pos":["adjectival nouns or quasi-adjectives (keiyodoshi)","noun (common) (futsuumeishi)"],"gloss":[{"value":"open-minded","lang":"eng"},{"value":"receptive","lang":"eng"},{"value":"free from preconceived ideas","lang":"eng"}]}]},{"ent_seq":1232780,"k_ele":[{"keb":"虚像","ke_pri":["news2","nf30"]}],"r_ele":[{"reb":"きょぞう","re_pri":["news2","nf30"]}],"sense":[{"pos":["noun (common) (futsuumeishi)","nouns which may take the genitive case particle 'no'"],"xref":["実像・じつぞう・1"],"field":["physics"],"gloss":[{"value":"virtual image","lang":"eng"}]},{"pos":["noun (common) (futsuumeishi)","nouns which may take the genitive case particle 'no'"],"xref":["実像・じつぞう・2"],"gloss":[{"value":"false image","lang":"eng"},{"value":"pretense","lang":"eng"},{"value":"pretence","lang":"eng"}]}]},{"ent_seq":1232790,"k_ele":[{"keb":"虚脱","ke_pri":["news2","nf34"]}],"r_ele":[{"reb":"きょだつ","re_pri":["news2","nf34"]}],"sense":[{"pos":["noun (common) (futsuumeishi)","noun or participle which takes the aux. verb suru","intransitive verb"],"gloss":[{"value":"lethargy","lang":"eng"},{"value":"despondency","lang":"eng"},{"value":"mental numbness","lang":"eng"}]},{"pos":["noun (common) (futsuumeishi)","noun or participle which takes the aux. verb suru","intransitive verb"],"field":["medicine"],"gloss":[{"value":"(physical) collapse","lang":"eng"},{"value":"prostration","lang":"eng"}]}]},{"ent_seq":1232810,"k_ele":[{"keb":"虚無","ke_pri":["ichi1","news2","nf34"]}],"r_ele":[{"reb":"きょむ","re_pri":["ichi1","news2","nf34"]}],"sense":[{"pos":["noun (common) (futsuumeishi)"],"gloss":[{"value":"nihility","lang":"eng"},{"value":"nothingness","lang":"eng"}]}]},{"ent_seq":1232850,"k_ele":[{"keb":"虚礼","ke_pri":["news2","nf46"]}],"r_ele":[{"reb":"きょれい","re_pri":["news2","nf46"]}],"sense":[{"pos":["noun (common) (futsuumeishi)"],"gloss":[{"value":"empty (useless) formalities","lang":"eng"}]}]},{"ent_seq":1245370,"k_ele":[{"keb":"虚しい","ke_pri":["spec1"]},{"keb":"空しい","ke_pri":["ichi1"]}],"r_ele":[{"reb":"むなしい","re_pri":["ichi1","spec1"]}],"sense":[{"pos":["adjective (keiyoushi)"],"gloss":[{"value":"empty","lang":"eng"},{"value":"void","lang":"eng"},{"value":"vacant","lang":"eng"}]},{"pos":["adjective (keiyoushi)"],"gloss":[{"value":"vain","lang":"eng"},{"value":"fruitless","lang":"eng"},{"value":"futile","lang":"eng"},{"value":"ineffective","lang":"eng"}]},{"pos":["adjective (keiyoushi)"],"xref":["空しくなる"],"gloss":[{"value":"lifeless","lang":"eng"}]}]},{"ent_seq":1609670,"k_ele":[{"keb":"虚栄心","ke_pri":["ichi1"]}],"r_ele":[{"reb":"きょえいしん","re_pri":["ichi1"]}],"sense":[{"pos":["noun (common) (futsuumeishi)"],"gloss":[{"value":"vanity","lang":"eng"}]}]},{"ent_seq":1776200,"k_ele":[{"keb":"虚実","ke_pri":["news2","nf39"]}],"r_ele":[{"reb":"きょじつ","re_pri":["news2","nf39"]}],"sense":[{"pos":["noun (common) (futsuumeishi)"],"gloss":[{"value":"falsehood and truth","lang":"eng"},{"value":"fiction and fact","lang":"eng"}]}]}]