[{"ent_seq":1550980,"k_ele":[{"keb":"陸","ke_pri":["ichi1","news1","nf05"]}],"r_ele":[{"reb":"りく","re_pri":["ichi1","news1","nf05"]},{"reb":"おか"}],"sense":[{"pos":["noun (common) (futsuumeishi)"],"gloss":[{"value":"land","lang":"eng"},{"value":"shore","lang":"eng"}]}]},{"ent_seq":1551000,"k_ele":[{"keb":"陸運","ke_pri":["news2","nf32"]}],"r_ele":[{"reb":"りくうん","re_pri":["news2","nf32"]}],"sense":[{"pos":["noun (common) (futsuumeishi)"],"gloss":[{"value":"land transportation","lang":"eng"}]}]},{"ent_seq":1551020,"k_ele":[{"keb":"陸軍","ke_pri":["ichi1","news1","nf06"]}],"r_ele":[{"reb":"りくぐん","re_pri":["ichi1","news1","nf06"]}],"sense":[{"pos":["noun (common) (futsuumeishi)"],"gloss":[{"value":"army","lang":"eng"}]}]},{"ent_seq":1551050,"k_ele":[{"keb":"陸上","ke_pri":["ichi1","news1","nf05"]}],"r_ele":[{"reb":"りくじょう","re_pri":["ichi1","news1","nf05"]}],"sense":[{"pos":["noun (common) (futsuumeishi)","nouns which may take the genitive case particle 'no'"],"gloss":[{"value":"(on) land","lang":"eng"},{"value":"ground","lang":"eng"},{"value":"shore","lang":"eng"}]},{"pos":["noun (common) (futsuumeishi)"],"xref":["陸上競技"],"misc":["abbreviation"],"gloss":[{"value":"track and field","lang":"eng"},{"value":"athletics","lang":"eng"}]}]},{"ent_seq":1551060,"k_ele":[{"keb":"陸上競技","ke_pri":["news1","nf09"]}],"r_ele":[{"reb":"りくじょうきょうぎ","re_pri":["news1","nf09"]}],"sense":[{"pos":["noun (common) (futsuumeishi)"],"gloss":[{"value":"track and field","lang":"eng"},{"value":"athletics","lang":"eng"}]}]},{"ent_seq":1551080,"k_ele":[{"keb":"陸戦","ke_pri":["news2","nf47"]}],"r_ele":[{"reb":"りくせん","re_pri":["news2","nf47"]}],"sense":[{"pos":["noun (common) (futsuumeishi)"],"gloss":[{"value":"land war","lang":"eng"}]}]},{"ent_seq":1551150,"k_ele":[{"keb":"陸路","ke_pri":["news1","nf18"]}],"r_ele":[{"reb":"りくろ","re_pri":["news1","nf18"]}],"sense":[{"pos":["noun (common) (futsuumeishi)"],"gloss":[{"value":"land route","lang":"eng"},{"value":"overland route","lang":"eng"}]},{"pos":["adverb (fukushi)"],"gloss":[{"value":"by land","lang":"eng"},{"value":"overland","lang":"eng"}]}]},{"ent_seq":1612250,"k_ele":[{"keb":"陸橋","ke_pri":["ichi1","news2","nf45"]}],"r_ele":[{"reb":"りっきょう","re_pri":["ichi1","news2","nf45"]},{"reb":"りくきょう"}],"sense":[{"pos":["noun (common) (futsuumeishi)"],"gloss":[{"value":"bridge (over a road or railway)","lang":"eng"},{"value":"overpass","lang":"eng"},{"value":"flyover","lang":"eng"},{"value":"viaduct","lang":"eng"}]},{"pos":["noun (common) (futsuumeishi)"],"field":["geography"],"gloss":[{"value":"land bridge","lang":"eng"}]}]},{"ent_seq":1644310,"k_ele":[{"keb":"陸揚げ","ke_pri":["news2","nf28"]},{"keb":"陸上げ","ke_inf":["rarely used kanji form"]},{"keb":"陸揚","ke_inf":["search-only kanji form"]},{"keb":"陸あげ","ke_inf":["search-only kanji form"]}],"r_ele":[{"reb":"りくあげ","re_pri":["news2","nf28"]}],"sense":[{"pos":["noun (common) (futsuumeishi)","noun or participle which takes the aux. verb suru","transitive verb"],"gloss":[{"value":"unloading (a ship)","lang":"eng"},{"value":"landing","lang":"eng"}]}]},{"ent_seq":1644320,"k_ele":[{"keb":"陸地","ke_pri":["news2","nf25"]}],"r_ele":[{"reb":"りくち","re_pri":["news2","nf25"]}],"sense":[{"pos":["noun (common) (futsuumeishi)","nouns which may take the genitive case particle 'no'"],"gloss":[{"value":"land","lang":"eng"}]}]},{"ent_seq":1644330,"k_ele":[{"keb":"陸上自衛隊","ke_pri":["news1","nf09"]}],"r_ele":[{"reb":"りくじょうじえいたい","re_pri":["news1","nf09"]}],"sense":[{"pos":["noun (common) (futsuumeishi)"],"gloss":[{"value":"Japan Ground Self-Defense Force","lang":"eng"},{"value":"JGSDF","lang":"eng"}]}]},{"ent_seq":1823900,"k_ele":[{"keb":"陸海","ke_pri":["news1","nf19"]}],"r_ele":[{"reb":"りくかい","re_pri":["news1","nf19"]},{"reb":"りっかい"}],"sense":[{"pos":["noun (common) (futsuumeishi)"],"gloss":[{"value":"land and sea","lang":"eng"}]},{"pos":["noun (common) (futsuumeishi)"],"xref":["陸軍","海軍"],"gloss":[{"value":"army and navy","lang":"eng"}]}]},{"ent_seq":1823940,"k_ele":[{"keb":"陸送","ke_pri":["news2","nf41"]}],"r_ele":[{"reb":"りくそう","re_pri":["news2","nf41"]}],"sense":[{"pos":["noun (common) (futsuumeishi)","noun or participle which takes the aux. verb suru","transitive verb"],"gloss":[{"value":"land transportation","lang":"eng"}]}]},{"ent_seq":1824020,"k_ele":[{"keb":"陸続き","ke_pri":["news2","nf38"]}],"r_ele":[{"reb":"りくつづき","re_pri":["news2","nf38"]}],"sense":[{"pos":["noun (common) (futsuumeishi)","nouns which may take the genitive case particle 'no'"],"gloss":[{"value":"being joined by land","lang":"eng"}]}]}]